[
  {
    "type": "filter_vaultentrytype",
    "message0": "VaultEntryType Filter %1 type %2",
    "args0": [
      {
        "type": "input_dummy",
        "align": "RIGHT"
      },
      {
        "type": "input_value",
        "name": "TYPE",
        "check": "VaultEntryType",
        "align": "RIGHT"
      }
    ],
    "inputsInline": false,
    "previousStatement": "Filter",
    "nextStatement": "Filter",
    "colour": 210,
    "tooltip": "Remove all entries that are not the given type",
    "helpUrl": ""
  },
  {
    "type": "filter_timespan",
    "message0": "Timespan Filter %1 from %2 until %3",
    "args0": [
      {
        "type": "input_dummy"
      },
      {
        "type": "input_value",
        "name": "START",
        "check": "DateTime",
        "align": "RIGHT"
      },
      {
        "type": "input_value",
        "name": "END",
        "check": "DateTime",
        "align": "RIGHT"
      }
    ],
    "inputsInline": false,
    "previousStatement": "Filter",
    "nextStatement": "Filter",
    "colour": 210,
    "tooltip": "Remove all entries that are not in the given timespan",
    "helpUrl": ""
  },
  {
    "type": "filter_and",
    "message0": "And Filter %1 %2",
    "args0": [
      {
        "type": "input_dummy"
      },
      {
        "type": "input_statement",
        "name": "FILTERS",
        "check": "Filter"
      }
    ],
    "previousStatement": "Filter",
    "nextStatement": "Filter",
    "colour": 210,
    "tooltip": "Remove all entries that do not match all contained filters",
    "helpUrl": ""
  }
]